pandas_historical/__init__.py
pandas_historical-0.1.2.dist-info/LICENSE
pandas_historical-0.1.2.dist-info/METADATA
pandas_historical-0.1.2.dist-info/WHEEL
pandas_historical-0.1.2.dist-info/entry_points.txt
pandas_historical-0.1.2.dist-info/top_level.txt
pandas_historical-0.1.2.dist-info/RECORD
